{"cameraMode":{"drawMode":0,"name":"Shaded","section":"Shading Mode"},"sceneLighting":true,"audioPlay":false,"sceneViewState":{"m_AlwaysRefresh":false,"showFog":true,"showSkybox":true,"showFlares":true,"showImageEffects":true,"showParticleSystems":true,"showVisualEffectGraphs":true,"m_FxEnabled":true},"in2DMode":false,"pivot":{"x":-18.451953887939454,"y":-8.17934513092041,"z":6.7192583084106449},"rotation":{"x":0.1781872659921646,"y":-0.4867202639579773,"z":0.10248471796512604,"w":0.850784957408905},"size":13.133177757263184,"orthographic":false}